README.txt
setup.py
exchange_rates/__init__.py
exchange_rates.egg-info/PKG-INFO
exchange_rates.egg-info/SOURCES.txt
exchange_rates.egg-info/dependency_links.txt
exchange_rates.egg-info/requires.txt
exchange_rates.egg-info/top_level.txt