Metadata-Version: 1.0
Name: exchange-rates
Version: 1.0.1
Summary: Retrives currency exchange rates from http://api.fixer.io/
Home-page: http://exchange_rates.lukeshiner.com
Author: Luke Shiner
Author-email: luke@lukeshiner.com
License: UNKNOWN
Keywords: exchange rates,currency,api
Platform: UNKNOWN
